{"trial_id": "00", "hyperparameters": {"space": [{"class_name": "Int", "config": {"name": "units", "default": null, "conditions": [], "min_value": 32, "max_value": 512, "step": 32, "sampling": "linear"}}, {"class_name": "Choice", "config": {"name": "activation", "default": "relu", "conditions": [], "values": ["relu", "tanh"], "ordered": false}}, {"class_name": "Float", "config": {"name": "l1", "default": 1e-06, "conditions": [], "min_value": 1e-06, "max_value": 0.001, "step": null, "sampling": "log"}}, {"class_name": "Float", "config": {"name": "l2", "default": 1e-06, "conditions": [], "min_value": 1e-06, "max_value": 0.001, "step": null, "sampling": "log"}}, {"class_name": "Int", "config": {"name": "units2", "default": null, "conditions": [], "min_value": 32, "max_value": 512, "step": 32, "sampling": "linear"}}, {"class_name": "Choice", "config": {"name": "activation2", "default": "relu", "conditions": [], "values": ["relu", "tanh"], "ordered": false}}, {"class_name": "Int", "config": {"name": "units3", "default": null, "conditions": [], "min_value": 24, "max_value": 512, "step": 32, "sampling": "linear"}}, {"class_name": "Float", "config": {"name": "l22", "default": 1e-06, "conditions": [], "min_value": 1e-06, "max_value": 0.001, "step": null, "sampling": "log"}}, {"class_name": "Int", "config": {"name": "units4", "default": null, "conditions": [], "min_value": 224, "max_value": 512, "step": 32, "sampling": "linear"}}, {"class_name": "Int", "config": {"name": "units5", "default": null, "conditions": [], "min_value": 24, "max_value": 512, "step": 32, "sampling": "linear"}}, {"class_name": "Float", "config": {"name": "l23", "default": 1e-06, "conditions": [], "min_value": 1e-06, "max_value": 0.001, "step": null, "sampling": "log"}}, {"class_name": "Choice", "config": {"name": "learning_rate", "default": 0.01, "conditions": [], "values": [0.01, 0.001, 0.0001], "ordered": true}}], "values": {"units": 448, "activation": "tanh", "l1": 0.0001458098376154108, "l2": 7.967256753528906e-06, "units2": 416, "activation2": "relu", "units3": 88, "l22": 1.3947514249236324e-05, "units4": 448, "units5": 408, "l23": 1.537789381718759e-05, "learning_rate": 0.01}}, "metrics": {"metrics": {"accuracy": {"direction": "max", "observations": [{"value": [0.9487704932689667], "step": 12}]}, "loss": {"direction": "min", "observations": [{"value": [5.416309833526611], "step": 12}]}, "val_accuracy": {"direction": "max", "observations": [{"value": [0.9363636374473572], "step": 12}]}, "val_loss": {"direction": "min", "observations": [{"value": [5.500213146209717], "step": 12}]}, "learning_rate": {"direction": "min", "observations": [{"value": [0.0024999999441206455], "step": 12}]}}}, "score": 0.9363636374473572, "best_step": 12, "status": "COMPLETED", "message": null}